fds/__init__.py
fds/sdk/__init__.py
fds/sdk/FactSetPeople/__init__.py
fds/sdk/FactSetPeople/api_client.py
fds/sdk/FactSetPeople/configuration.py
fds/sdk/FactSetPeople/exceptions.py
fds/sdk/FactSetPeople/model_utils.py
fds/sdk/FactSetPeople/rest.py
fds/sdk/FactSetPeople/api/__init__.py
fds/sdk/FactSetPeople/api/company_api.py
fds/sdk/FactSetPeople/api/job_history_api.py
fds/sdk/FactSetPeople/api/profiles_api.py
fds/sdk/FactSetPeople/apis/__init__.py
fds/sdk/FactSetPeople/model/__init__.py
fds/sdk/FactSetPeople/model/company_compensation.py
fds/sdk/FactSetPeople/model/company_compensation_request.py
fds/sdk/FactSetPeople/model/company_compensation_response.py
fds/sdk/FactSetPeople/model/company_ids.py
fds/sdk/FactSetPeople/model/company_people.py
fds/sdk/FactSetPeople/model/company_people_request.py
fds/sdk/FactSetPeople/model/company_people_response.py
fds/sdk/FactSetPeople/model/company_positions.py
fds/sdk/FactSetPeople/model/company_positions_request.py
fds/sdk/FactSetPeople/model/company_positions_response.py
fds/sdk/FactSetPeople/model/company_stats.py
fds/sdk/FactSetPeople/model/company_stats_request.py
fds/sdk/FactSetPeople/model/company_stats_response.py
fds/sdk/FactSetPeople/model/error_response.py
fds/sdk/FactSetPeople/model/error_response_sub_errors.py
fds/sdk/FactSetPeople/model/function.py
fds/sdk/FactSetPeople/model/ids.py
fds/sdk/FactSetPeople/model/job.py
fds/sdk/FactSetPeople/model/level.py
fds/sdk/FactSetPeople/model/mb_type.py
fds/sdk/FactSetPeople/model/people_jobs_request.py
fds/sdk/FactSetPeople/model/people_jobs_response.py
fds/sdk/FactSetPeople/model/people_profiles_request.py
fds/sdk/FactSetPeople/model/people_profiles_response.py
fds/sdk/FactSetPeople/model/position.py
fds/sdk/FactSetPeople/model/profile.py
fds/sdk/FactSetPeople/model/status.py
fds/sdk/FactSetPeople/model/type.py
fds/sdk/FactSetPeople/models/__init__.py
fds.sdk.FactSetPeople-1.0.15.dist-info/LICENSE
fds.sdk.FactSetPeople-1.0.15.dist-info/METADATA
fds.sdk.FactSetPeople-1.0.15.dist-info/WHEEL
fds.sdk.FactSetPeople-1.0.15.dist-info/top_level.txt
fds.sdk.FactSetPeople-1.0.15.dist-info/RECORD
